odoo/addons/account_invoice_bank_brand/README.rst
odoo/addons/account_invoice_bank_brand/__init__.py
odoo/addons/account_invoice_bank_brand/__manifest__.py
odoo/addons/account_invoice_bank_brand/models/__init__.py
odoo/addons/account_invoice_bank_brand/models/account_invoice.py
odoo/addons/account_invoice_bank_brand/models/res_brand.py
odoo/addons/account_invoice_bank_brand/readme/CONTRIBUTORS.rst
odoo/addons/account_invoice_bank_brand/readme/DESCRIPTION.rst
odoo/addons/account_invoice_bank_brand/readme/USAGE.rst
odoo/addons/account_invoice_bank_brand/static/description/icon.png
odoo/addons/account_invoice_bank_brand/static/description/index.html
odoo/addons/account_invoice_bank_brand/tests/__init__.py
odoo/addons/account_invoice_bank_brand/tests/test_account_invoice.py
odoo/addons/account_invoice_bank_brand/views/res_brand.xml
odoo12_addon_account_invoice_bank_brand-12.0.1.0.0.99.dev1.dist-info/METADATA
odoo12_addon_account_invoice_bank_brand-12.0.1.0.0.99.dev1.dist-info/WHEEL
odoo12_addon_account_invoice_bank_brand-12.0.1.0.0.99.dev1.dist-info/top_level.txt
odoo12_addon_account_invoice_bank_brand-12.0.1.0.0.99.dev1.dist-info/RECORD
